pynnex/__init__.py
pynnex/core.py
pynnex/utils.py
pynnex/_internal/log_colors.py
pynnex/_internal/log_config.py
pynnex/contrib/extensions/__init__.py
pynnex/contrib/extensions/property.py
pynnex/contrib/patterns/__init__.py
pynnex/contrib/patterns/worker/__init__.py
pynnex/contrib/patterns/worker/decorators.py
PynneX-1.1.5.dist-info/LICENSE
PynneX-1.1.5.dist-info/METADATA
PynneX-1.1.5.dist-info/WHEEL
PynneX-1.1.5.dist-info/top_level.txt
PynneX-1.1.5.dist-info/RECORD
