Metadata-Version: 2.2
Name: PynneX
Version: 1.1.5
Summary: A Python Emitter-Listener library
Author-email: San Kim <nexconnect.io@gmail.com>
License: MIT
Project-URL: Homepage, https://github.com/nexconnectio/pynnex
Project-URL: Repository, https://github.com/nexconnectio/pynnex
Project-URL: Documentation, https://github.com/nexconnectio/pynnex#readme
Project-URL: Issues, https://github.com/nexconnectio/pynnex/issues
Keywords: emitter,listener,signals,slots,signal-slot,decorator,asyncio,thread-safe,multithreading,pubsub,publisher,subscriber
Classifier: Development Status :: 3 - Alpha
Classifier: Intended Audience :: Developers
Classifier: License :: OSI Approved :: MIT License
Classifier: Programming Language :: Python :: 3
Classifier: Programming Language :: Python :: 3.10
Classifier: Programming Language :: Python :: 3.11
Classifier: Programming Language :: Python :: 3.12
Classifier: Programming Language :: Python :: 3.13
Classifier: Topic :: Software Development :: Libraries
Requires-Python: >=3.10
License-File: LICENSE
Provides-Extra: dev
Requires-Dist: pytest>=7.0; extra == "dev"
Requires-Dist: pytest-cov>=4.0; extra == "dev"
Requires-Dist: pytest-asyncio>=0.21.0; extra == "dev"
Requires-Dist: memory_profiler; extra == "dev"
